pixel2world/__init__.py
pixel2world/convert_data.py
pixel2world/coord_conversion.py
pixel2world/import_calibration.py
pixel2world-0.0.4.dist-info/LICENSE
pixel2world-0.0.4.dist-info/METADATA
pixel2world-0.0.4.dist-info/WHEEL
pixel2world-0.0.4.dist-info/top_level.txt
pixel2world-0.0.4.dist-info/RECORD
